{
  "dataList": [
    {
      "id": "get_10306_1",
      "desc": "Получение",
      "dlg": "Зовите меня Дон Кихот! Младшая сестрёнка Среднего пальца и преданная слуга Среднего брата! Рада познакомиться!"
    },
    {
      "id": "lobby_morning_10306_1",
      "desc": "Утреннее приветствие",
      "dlg": "Славного утреца! Известны ль вам вести, куда путь держит сегодня Средний братец? Извольте поделиться!"
    },
    {
      "id": "lobby_noon_10306_1",
      "desc": "Полуденное приветствие",
      "dlg": "Средний брат пригласил меня на обеденную трапезу! Порадуете своим присутствием? Он даже молвил, что заплатит за меня!"
    },
    {
      "id": "lobby_night_10306_1",
      "desc": "Вечернее приветствие",
      "dlg": "Не бывать вечере без вечеринки! Наши вечери всегда схожи с бурными вечеринками, наполненными задорными историями."
    },
    {
      "id": "smalltalk_10306_1",
      "desc": "Болтовня №1",
      "dlg": "Истинным грехом считается посягательство на жизни членов и семьи Среднего пальца! Навлечь стократную кару на таких негодяев — истинное правосудие!"
    },
    {
      "id": "smalltalk_10306_2",
      "desc": "Болтовня №2",
      "dlg": "Наш Средний брат много внимания уделяет виду своих локонов. Ходит молва, что он не жалеет никаких денег… <b>на изысканные парикмахерские</b> самых богатых портов."
    },
    {
      "id": "smalltalk_10306_3",
      "desc": "Болтовня №3",
      "dlg": "Пусть сила Среднего брата никогда не была под сомнением… порой я придаюсь раздумью, во сколько же сила его превосходит мою!"
    },
    {
      "id": "smalltalk_10306_4",
      "desc": "Болтовня после Связи №1",
      "dlg": "Ха-ха, почто же вы перешли нам дорогу? Что ж, теперь вам воздастся по заслугам!"
    },
    {
      "id": "smalltalk_10306_5",
      "desc": "Болтовня после Связи №2",
      "dlg": "Взирайте с чуткостью, ибо это… Книга возмездия. Здесь перечислены действия для достижения правосудия.\nНаписано в ней ваше имя, верно? Желаете ли вы, чтобы оно было стёрто? Тогда… вам придётся сгинуть."
    },
    {
      "id": "neglect_10306_1",
      "desc": "Бездействие",
      "dlg": "Важно использовать свободное время с пользой и держать книгу в порядке. Ибо однажды я стану Средней... нет, Старшей сестрой!"
    },
    {
      "id": "gacksung_10306_1",
      "desc": "Связь",
      "dlg": "Сам Средний брат предоставил мне возможность заняться целями в книге! Ха-ха, воистину прелестно! Я вложу всю себя в его ожидания!"
    },
    {
      "id": "formation_10306_1",
      "desc": "Вступление в команду",
      "dlg": "Есть негодяй, которого ждёт возмездие?!"
    },
    {
      "id": "battleentry_10306_1",
      "desc": "Выход на поле боя",
      "dlg": "Позвольте мне!"
    },
    {
      "id": "battle_select_10306_1",
      "desc": "Выбор в битве",
      "dlg": "Ха! Средний брат взывает меня?"
    },
    {
      "id": "battle_endcommand_10306_1",
      "desc": "Совершение атаки",
      "dlg": "Ха-ха! В атаку!"
    },
    {
      "id": "battle_enemy_break_10306_1",
      "desc": "Оглушение противника",
      "dlg": "Соберитесь, Книга гласит, что с этим надо разобраться на хладную голову."
    },
    {
      "id": "battle_break_10306_1",
      "desc": "Оглушение",
      "dlg": "Нет…"
    },
    {
      "id": "battle_kill_10306_1",
      "desc": "Убийство противника",
      "dlg": "Возмездие свершилось."
    },
    {
      "id": "battle_dead_10306_1",
      "desc": "Смерть",
      "dlg": "Неужели… сгину здесь… но… Средний палец не забудет…"
    },
    {
      "id": "choice_success_p_10306_2",
      "desc": "Успех проверки",
      "dlg": "Ха! Сложнее есть ль чего?"
    },
    {
      "id": "choice_fail_n_10306_1",
      "desc": "Провал проверки",
      "dlg": "Должно быть, силы воли мне не хватило…"
    },
    {
      "id": "battle_clear_10306_1",
      "desc": "Победный клич",
      "dlg": "И вот месть в конечном счёте свершилась! В вечер нам будет, что отметить!"
    },
    {
      "id": "battle_clear_ex_10306_1",
      "desc": "Победный клич совершенства",
      "dlg": "Посмотрим…  Да! Можно вычеркнуть целую колонку. Средний брат будет доволен, ибо я сыграла немалую роль в его миссии!"
    },
    {
      "id": "battle_defeat_10306_1",
      "desc": "Вой поражения",
      "dlg": "Не смейте забыть… Средний палец запомнит… Средний палец запишет… Вас будет ждать кара в сто крат."
    }
  ]
}