{
    "dataList": [
        {
            "id": "AaCePcBa",
            "name": "Отмечен",
            "desc": "Является приоритетной целью для атаки.",
            "summary": "",
            "undefined": "-"
        },
        {
            "id": "AaCePcBb",
            "name": "Дрейфующий обломок",
            "desc": "Начало хода: Получает 3 Дыхания and +2 счетчика Дыхания",
            "summary": "",
            "undefined": "-"
        },
        {
            "id": "AaCePcBc",
            "name": "Слепая Одержимость",
            "desc": "При 3+ счетчике, данный юнит становится оглушенным.",
            "summary": "",
            "undefined": "-"
        },
        {
            "id": "AaCePcBg",
            "name": "Личинка",
            "desc": "Конец хода: Накладывает Личинку на союзника с наибольшим ОЗ.\nНачало хода: Теряет СД равное счетчику Личинок на себе.",
            "summary": "",
            "undefined": "-"
        },
        {
            "id": "AaCePcBh",
            "name": "Зеленая Слизь",
            "desc": "Создает Зеленую Слизь в следующем ходу каждый раз, когда счетчик уменьшается",
            "summary": "",
            "undefined": "-"
        },
        {
            "id": "AaCePcBi",
            "name": "Сбивчивое Дыхание",
            "desc": "Конец Хода: Теряет 5 Дыхания.\nНаносит +50% больше урона и получает +50% больше урона",
            "summary": "",
            "undefined": "-"
        },
        {
            "id": "AaCePcBj",
            "name": "Метка Добычи",
            "desc": "Весь экипаж Пекода целятся на этот юнит.\nПолучает +50% больше урона от экипажа Пекода",
            "summary": "",
            "undefined": "-"
        },
        {
            "id": "AaCePcBk",
            "name": "Опутывание",
            "desc": "Если наложено по цели с Захватом, оглушает цель. Не работает против целей, которые уже оглушены.",
            "summary": "",
            "undefined": "-"
        },
        {
            "id": "AaCePcBl",
            "name": "Захват",
            "desc": "Если наложено по цели с Опутыванием, оглушает цель. Не работает против целей, которые уже оглушены.",
            "summary": "",
            "undefined": "-"
        },
        {
            "id": "AaCePcBn",
            "name": "Неоспоримый Приказ",
            "desc": "Теряет 10% текущих ОЗ, когда использует навык. Финальная Мощь навыка +1\nПри ударе, Ахав исцеляет 8 СД; накладывает 2 Дыхания на себя и Ахав",
            "summary": "Теряет ОЗ при использовании навыка; Финальная Мощь +1",
            "undefined": "-"
        },
        {
            "id": "AaCePcBo",
            "name": "Э.Г.О Пипа",
            "desc": "Начало хода: Исцеляет 3 СД за каждый счетчик.\nУменьшает при использовании Тяжесть Вины просле провала Уворота.\nКонец хода: Если счетчик равен 0, становится оглушенным",
            "summary": "Исцеляет СД за счетчик. Уменьшает счетчик при использовании определенных навыков после провала Уворота.",
            "undefined": "-"
        },
        {
            "id": "AaCePcBp",
            "name": "Э.Г.О Старбака",
            "desc": "Начало хода: Получает 1 Защищённость за каждые 6 счетчика.\nУменьшается за каждую сломанную Монету в Столкновении против целей с Меткой Добычи.\nКонец Хода: Если счетчик равен 0, становится оглушенным.",
            "summary": "Получает Защищённость за счетчик. Уменьшает счетчик в Столкновении против определенных целей.",
            "undefined": "-"
        },
        {
            "id": "AaCePcBq",
            "name": "Э.Г.О Квикег",
            "desc": "Конец Хода: Получает счетчик при Защите.\nКонец Хода: Теряет счетчик если не имеет Щит или Бледное Искупление.\nКонец Хода: Если счетчик равен 0, становится оглушенным.",
            "summary": "Конец Хода: В зависимости если данный юнит Защищён или нет, теряет или получает счетчик.",
            "undefined": "-"
        },
        {
            "id": "AaCePcBe",
            "name": "Бледная Паника",
            "desc": "Эффективность потери СД +2",
            "summary": "",
            "undefined": "-"
        },
        {
            "id": "AaCePcBf",
            "name": "Бледная Паника",
            "desc": "Получает 2 Связывания в Конце Хода.\nКаждая подбрасываемая монетка этого юнита выпадает решкой.",
            "summary": "",
            "undefined": "-"
        },
        {
            "id": "AaCePcBr",
            "name": "Поддержка Барьера",
            "desc": "Уменьшает счетчик за кол-во полученного урона.\nНе истекает в Конце Хода.\nКонец Хода: Если счетчик равен 0, становится оглушенным в следующем ходу.",
            "summary": "",
            "undefined": "-"
        },
        {
            "id": "AaCePcBs",
            "name": "Поддержка Защиты",
            "desc": "Перенаправляет навыки нацеленные на Ахав, на слот этого юнита.\nЮнит с этим эффектом имеет неограниченный Вес Атаки",
            "summary": "",
            "undefined": "-"
        },
        {
            "id": "AaCePcBt",
            "name": "Поддержка Атаки",
            "desc": "После атаки Ахав, совершает ненаправленную атаку против цели которую атаковал Ахав.\nНавык используемый в этом действии имеет тот же Уровень Атаки, значение Монет и эффектов, как у навыка 'Я Следую Приказам...' юнита.",
            "summary": "",
            "undefined": "-"
        }
    ]
}
