{
  "dataList": [
    {
      "id": 2030511,
      "levelList": [
        {
          "level": 1,
          "name": "Камни желаний",
          "abName": "Воспевания падоге",
          "desc": "",
          "coinlist": [
            {
              "coindescs": [
                {
                  "desc": "[OnSucceedAttack] Повышает счётчик <sprite name=\"Laceration\"><color=#e30000><u><link=\"Laceration\">Кровотечения</link></u></color> на 3"
                },
                {
                  "desc": "[OnSucceedAttack] Наносит 4 <sprite name=\"Vibration\"><color=#e30000><u><link=\"Vibration\">Тремора</link></u></color>"
                }
              ]
            }
          ]
        },
        {
          "level": 3,
          "name": "Камни желаний",
          "abName": "Воспевания падоге",
          "desc": "",
          "coinlist": [
            {
              "coindescs": [
                {
                  "desc": "[OnSucceedAttack] Повышает счётчик <sprite name=\"Laceration\"><color=#e30000><u><link=\"Laceration\">Кровотечения</link></u></color> на 4"
                },
                {
                  "desc": "[OnSucceedAttack] Наносит 5 <sprite name=\"Vibration\"><color=#e30000><u><link=\"Vibration\">Тремора</link></u></color>"
                },
                {
                  "desc": "[OnSucceedAttackHead] Наносит 2 <sprite name=\"Paralysis\"><color=#e30000><u><link=\"Paralysis\">Паралича</link></u></color>"
                }
              ]
            }
          ]
        },
        {
          "level": 4,
          "name": "Камни желаний",
          "abName": "Воспевания падоге",
          "desc": "",
          "coinlist": [
            {
              "coindescs": [
                {
                  "desc": "[OnSucceedAttack] Повышает счётчик <sprite name=\"Laceration\"><color=#e30000><u><link=\"Laceration\">Кровотечения</link></u></color> на 4"
                },
                {
                  "desc": "[OnSucceedAttack] Наносит 5 <sprite name=\"Vibration\"><color=#e30000><u><link=\"Vibration\">Тремора</link></u></color>"
                },
                {
                  "desc": "[OnSucceedAttackHead] Наносит 2 <sprite name=\"Paralysis\"><color=#e30000><u><link=\"Paralysis\">Паралича</link></u></color>"
                }
              ]
            }
          ]
        }
      ]
    },
    {
      "id": 2030521,
      "levelList": [
        {
          "level": 1,
          "name": "Камни желаний",
          "abName": "Воспевания падоге",
          "desc": "[CantIdentify]\nСлучайная цель\n",
          "coinlist": [
            {
              "coindescs": [
                {
                  "desc": "[CriticalOnSucceedAttack] <sprite name=\"VibrationExplosion\"><color=#e30000><u><link=\"VibrationExplosion\">Провоцирует Тремор</link></u></color>"
                },
                {
                  "desc": "[CriticalOnSucceedAttack] Наносит 4 <sprite name=\"Laceration\"><color=#e30000><u><link=\"Laceration\">Кровотечения</link></u></color>"
                },
                {
                  "desc": "[OnSucceedAttackTail] <sprite name=\"VibrationExplosion\"><color=#e30000><u><link=\"VibrationExplosion\">Провоцирует Тремор</link></u></color>"
                },
                {
                  "desc": "[OnSucceedAttack] <sprite name=\"VibrationExplosion\"><color=#e30000><u><link=\"VibrationExplosion\">Провоцирует Тремор</link></u></color>. Понижает счётчик <sprite name=\"Vibration\"><color=#e30000><u><link=\"Vibration\">Тремора</link></u></color> на 2"
                }
              ]
            }
          ]
        },
        {
          "level": 3,
          "name": "Камни желаний",
          "abName": "Воспевания падоге",
          "desc": "[CantIdentify]\nСлучайная цель",
          "coinlist": [
            {
              "coindescs": [
                {
                  "desc": "[CriticalOnSucceedAttack] <sprite name=\"VibrationExplosion\"><color=#e30000><u><link=\"VibrationExplosion\">Провоцирует Тремор</link></u></color>"
                },
                {
                  "desc": "[CriticalOnSucceedAttack] Наносит 6 <sprite name=\"Laceration\"><color=#e30000><u><link=\"Laceration\">Кровотечения</link></u></color>"
                },
                {
                  "desc": "[OnSucceedAttackTail] <sprite name=\"VibrationExplosion\"><color=#e30000><u><link=\"VibrationExplosion\">Провоцирует Тремор</link></u></color>"
                },
                {
                  "desc": "[OnSucceedAttack] <sprite name=\"VibrationExplosion\"><color=#e30000><u><link=\"VibrationExplosion\">Провоцирует Тремор</link></u></color>. Понижает счётчик <sprite name=\"Vibration\"><color=#e30000><u><link=\"Vibration\">Тремора</link></u></color> на 2"
                }
              ]
            }
          ]
        },
        {
          "level": 4,
          "name": "Камни желаний",
          "abName": "Воспевания падоге",
          "desc": "[CantIdentify]\nСлучайная цель",
          "coinlist": [
            {
              "coindescs": [
                {
                  "desc": "[CriticalOnSucceedAttack] <sprite name=\"VibrationExplosion\"><color=#e30000><u><link=\"VibrationExplosion\">Провоцирует Тремор</link></u></color>"
                },
                {
                  "desc": "[CriticalOnSucceedAttack] Наносит 8 <sprite name=\"Laceration\"><color=#e30000><u><link=\"Laceration\">Кровотечения</link></u></color>"
                },
                {
                  "desc": "[OnSucceedAttackTail] <sprite name=\"VibrationExplosion\"><color=#e30000><u><link=\"VibrationExplosion\">Провоцирует Тремор</link></u></color>"
                },
                {
                  "desc": "[OnSucceedAttack] <sprite name=\"VibrationExplosion\"><color=#e30000><u><link=\"VibrationExplosion\">Провоцирует Тремор</link></u></color>. Понижает счётчик <sprite name=\"Vibration\"><color=#e30000><u><link=\"Vibration\">Тремора</link></u></color> на 2"
                }
              ]
            }
          ]
        }
      ]
    },
    {
      "id": 2030611,
      "levelList": [
        {
          "level": 1,
          "name": "Электрическое блеяние",
          "abName": "Снящаяся электроовца",
          "desc": "[BeforeAttack] Кол-во целей +(резон. Зависти - 2) (До 1)\n[BeforeAttack] При 20 и более на счётчике <sprite name=\"Charge\"><color=#f8c200><u><link=\"Charge\">Заряда</link></u></color>, тратит 20 единиц счётчика <sprite name=\"Charge\"><color=#f8c200><u><link=\"Charge\">Заряда</link></u></color>, чтобы получить +30% урона",
          "coinlist": [
            {
              "coindescs": [
                {
                  "desc": "[EnemyKill] Повышает свой счётчик <sprite name=\"Charge\"><color=#f8c200><u><link=\"Charge\">Заряда</link></u></color> на 2"
                }
              ]
            }
          ]
        },
        {
          "level": 3,
          "name": "Электрическое блеяние",
          "abName": "Снящаяся электроовца",
          "desc": "[BeforeAttack] Кол-во целей +(резон. Зависти - 2) (До 2)\n[BeforeAttack] Повышает урон на (резон. Зависти - 3) x 5% (До 15%)\n[BeforeAttack] При 20 и более на счётчике <sprite name=\"Charge\"><color=#f8c200><u><link=\"Charge\">Заряда</link></u></color>, тратит 20 единиц счётчика <sprite name=\"Charge\"><color=#f8c200><u><link=\"Charge\">Заряда</link></u></color>, чтобы получить +35% урона",
          "coinlist": [
            {
              "coindescs": [
                {
                  "desc": "[EnemyKill] Повышает свой счётчик <sprite name=\"Charge\"><color=#f8c200><u><link=\"Charge\">Заряда</link></u></color> на 2"
                }
              ]
            }
          ]
        },
        {
          "level": 4,
          "name": "Электрическое блеяние",
          "abName": "Снящаяся электроовца",
          "desc": "[BeforeAttack] Кол-во целей +(резон. Зависти - 2) (До 3)\n[BeforeAttack] Повышает урон на (резон. Зависти - 3) x 10% (До 30%)\n[BeforeAttack] При 20 и более на счётчике <sprite name=\"Charge\"><color=#f8c200><u><link=\"Charge\">Заряда</link></u></color>, тратит 20 единиц счётчика <sprite name=\"Charge\"><color=#f8c200><u><link=\"Charge\">Заряда</link></u></color>, чтобы получить +40% урона",
          "coinlist": [
            {
              "coindescs": [
                {
                  "desc": "[EnemyKill] Повышает свой счётчик <sprite name=\"Charge\"><color=#f8c200><u><link=\"Charge\">Заряда</link></u></color> на 2"
                }
              ]
            }
          ]
        }
      ]
    },
    {
      "id": 2030621,
      "levelList": [
        {
          "level": 1,
          "name": "Электрическое блеяние",
          "abName": "Снящаяся электроовца",
          "desc": "[CantIdentify]\nСлучайные цели\n[BeforeAttack] Кол-во целей +(резон. Зависти - 2) (До 1)\n[BeforeAttack] Повышает урон на (резон. Зависти - 3) x 5% (До 15%)\n[BeforeAttack] При менее 20 на счётчике <sprite name=\"Charge\"><color=#f8c200><u><link=\"Charge\">Заряда</link></u></color>, восполняет счётчик <sprite name=\"Charge\"><color=#f8c200><u><link=\"Charge\">Заряда</link></u></color> до 20 через трату 1.5% от максимальных ОЗ за единицу <sprite name=\"Charge\"><color=#f8c200><u><link=\"Charge\">Заряда</link></u></color>\n[BeforeAttack] Тратит до 20 единиц счётчика <sprite name=\"Charge\"><color=#f8c200><u><link=\"Charge\">Заряда</link></u></color> для повышения урона на +2.5% за единицу <sprite name=\"Charge\"><color=#f8c200><u><link=\"Charge\">Заряда</link></u></color> (До 50%)",
          "coinlist": [
            {
              "coindescs": [
                {
                  "desc": "[EnemyKill] Повышает свой счётчик <sprite name=\"Charge\"><color=#f8c200><u><link=\"Charge\">Заряда</link></u></color> на 3"
                }
              ]
            }
          ]
        },
        {
          "level": 3,
          "name": "Электрическое блеяние",
          "abName": "Снящаяся электроовца",
          "desc": "[CantIdentify]\nСлучайные цели\n[BeforeAttack] Кол-во целей +(резон. Зависти - 2) (До <style=\"highlight\">2</style>)\n[BeforeAttack] Повышает урон на (резон. Зависти - 3) x <style=\"highlight\">8</style>% (До <style=\"highlight\">24</style>%)\n[BeforeAttack] При менее 20 на счётчике <sprite name=\"Charge\"><color=#f8c200><u><link=\"Charge\">Заряда</link></u></color>, восполняет счётчик <sprite name=\"Charge\"><color=#f8c200><u><link=\"Charge\">Заряда</link></u></color> до 20 через трату 1.5% от максимальных ОЗ за единицу <sprite name=\"Charge\"><color=#f8c200><u><link=\"Charge\">Заряда</link></u></color>\n[BeforeAttack] Тратит до 20 единиц счётчика <sprite name=\"Charge\"><color=#f8c200><u><link=\"Charge\">Заряда</link></u></color> для повышения урона на +<style=\"highlight\">3.5</style>% за единицу <sprite name=\"Charge\"><color=#f8c200><u><link=\"Charge\">Заряда</link></u></color> (До  <style=\"highlight\">70</style>%)",
          "coinlist": [
            {
              "coindescs": [
                {
                  "desc": "[EnemyKill] Повышает свой счётчик <sprite name=\"Charge\"><color=#f8c200><u><link=\"Charge\">Заряда</link></u></color> на 3"
                }
              ]
            }
          ]
        },
        {
          "level": 4,
          "name": "Электрическое блеяние",
          "abName": "Снящаяся электроовца",
          "desc": "[CantIdentify]\nСлучайные цели\n[BeforeAttack] Кол-во целей +(резон. Зависти - 2) (До <style=\"highlight\">3</style>)\n[BeforeAttack] Повышает урон на (резон. Зависти - 3) x <style=\"highlight\">12</style>% (До <style=\"highlight\">36</style>%)\n[BeforeAttack] При менее 20 на счётчике <sprite name=\"Charge\"><color=#f8c200><u><link=\"Charge\">Заряда</link></u></color>, восполняет счётчик <sprite name=\"Charge\"><color=#f8c200><u><link=\"Charge\">Заряда</link></u></color> до 20 через трату <style=\"highlight\">1</style>% от максимальных ОЗ за единицу <sprite name=\"Charge\"><color=#f8c200><u><link=\"Charge\">Заряда</link></u></color>\n[BeforeAttack] Тратит до 20 единиц счётчика <sprite name=\"Charge\"><color=#f8c200><u><link=\"Charge\">Заряда</link></u></color> для повышения урона на +<style=\"highlight\">5</style>% за единицу <sprite name=\"Charge\"><color=#f8c200><u><link=\"Charge\">Заряда</link></u></color> (До  <style=\"highlight\">100</style>%)",
          "coinlist": [
            {
              "coindescs": [
                {
                  "desc": "[EnemyKill] Повышает свой счётчик <sprite name=\"Charge\"><color=#f8c200><u><link=\"Charge\">Заряда</link></u></color> на 3"
                }
              ]
            }
          ]
        }
      ]
    },
    {
      "id": 2030711,
      "levelList": [
        {
          "level": 1,
          "name": "Жаждущая - Миркалла",
          "abName": "Четыре сотни Роз",
          "desc": "ОЗ этого Грешника не может упасть ниже 1 при использовании этого ЭГО.\nСила в Столкновении +1 за каждые 100 [BloodDinner_Accumulation] этим Грешником (макс. 2)\n[BeforeAttack] При значении меньше 50 [BloodDinner], наносит 1 [Laceration] за каждый Удар\n[EndSkill] На 3 хода, теряет 10 СД в Конце Хода.",
          "coinlist": [
            {
              "coindescs": [
                {
                  "desc": "[SuperCoin]"
                },
                {
                  "desc": "Наносит +0.1% больше урона за каждый [BloodDinner_Common_Accumulation] (макс. 10%)"
                }
              ]
            },
            {
              "coindescs": [
                {
                  "desc": "[SuperCoin]"
                },
                {
                  "desc": "При 100+ [BloodDinner_Common_Accumulation]: Наносит +0.1% больше урона за каждое значение (макс. 10%)"
                }
              ]
            },
            {
              "coindescs": [
                {
                  "desc": "[SuperCoin]"
                },
                {
                  "desc": "При 200+ [BloodDinner_Common_Accumulation]: Наносит +0.1% больше урона за каждое значение (макс. 20%)"
                }
              ]
            },
            {
              "coindescs": [
                {
                  "desc": "[SuperCoin]"
                },
                {
                  "desc": "При 300+ [BloodDinner_Common_Accumulation]: Наносит +0.1% больше урона за каждое значение (макс. 30%)"
                },
                {
                  "desc": "[WinDuelAttack] Наносит [ThirstyRose] основываясь на наибольшем Абсолютном резон. Похоти (макс. 3)"
                }
              ]
            }
          ]
        },
        {
          "level": 3,
          "name": "Жаждущая - Миркалла",
          "abName": "Четыре сотни Роз",
          "desc": "ОЗ этого Грешника не может упасть ниже 1 при использовании этого ЭГО.\n<style=\"highlight\">Если на цели имеется 10+ [Laceration], Сила Монет +1</style>\nСила в Столкновении +1 за каждые 100 [BloodDinner_Accumulation] этим Грешником (макс. <style=\"highlight\">3</style>)\n[BeforeAttack] При значении меньше <style=\"highlight\">75</style> [BloodDinner], наносит 1 [Laceration] за каждый Удар\n[EndSkill] На 3 хода, теряет 10 СД в Конце Хода.",
          "coinlist": [
            {
              "coindescs": [
                {
                  "desc": "[SuperCoin]"
                },
                {
                  "desc": "Наносит +0.1% больше урона за каждый [BloodDinner_Common_Accumulation] (макс. 10%)<style=\"highlight\"></style>"
                }
              ]
            },
            {
              "coindescs": [
                {
                  "desc": "[SuperCoin]"
                },
                {
                  "desc": "При 100+ [BloodDinner_Common_Accumulation]: Наносит +0.1% больше урона за каждое значение (макс. <style=\"highlight\">15</style>%)"
                }
              ]
            },
            {
              "coindescs": [
                {
                  "desc": "[SuperCoin]"
                },
                {
                  "desc": "При 200+ [BloodDinner_Common_Accumulation]: Наносит +0.1% больше урона за каждое значение (макс. <style=\"highlight\">25</style>%)"
                }
              ]
            },
            {
              "coindescs": [
                {
                  "desc": "[SuperCoin]"
                },
                {
                  "desc": "При 300+ [BloodDinner_Common_Accumulation]: Наносит +0.1% больше урона за каждое значение (макс. <style=\"highlight\">40</style>%)"
                },
                {
                  "desc": "[WinDuelAttack] Наносит [ThirstyRose] основываясь на наибольшем Абсолютном резон. Похоти (макс. 3)"
                }
              ]
            }
          ]
        },
        {
          "level": 4,
          "name": "Жаждущая - Миркалла",
          "abName": "Четыре сотни Роз",
          "desc": "ОЗ этого Грешника не может упасть ниже 1 при использовании этого ЭГО.\n<style=\"highlight\">Сила Монет +1 за каждые 10 [Laceration] на цели (макс. 2)</style>\nСила в Столкновении +1 за каждые 100 [BloodDinner_Accumulation] этим Грешником (макс. <style=\"highlight\">5</style>)\n[BeforeAttack] При значении меньше <style=\"highlight\">100</style> [BloodDinner], наносит 1 [Laceration] за каждый Удар\n[EndSkill] На 3 хода, теряет 10 СД в Конце Хода.",
          "coinlist": [
            {
              "coindescs": [
                {
                  "desc": "[SuperCoin]"
                },
                {
                  "desc": "Наносит +0.1% больше урона за каждый [BloodDinner_Common_Accumulation] (макс. 10%)"
                }
              ]
            },
            {
              "coindescs": [
                {
                  "desc": "[SuperCoin]"
                },
                {
                  "desc": "При 100+ [BloodDinner_Common_Accumulation]: Наносит +0.1% больше урона за каждое значение (макс. <style=\"highlight\">20</style>%)"
                }
              ]
            },
            {
              "coindescs": [
                {
                  "desc": "[SuperCoin]"
                },
                {
                  "desc": "При 200+ [BloodDinner_Common_Accumulation]: Наносит +0.1% больше урона за каждое значение (макс. <style=\"highlight\">30</style>%)"
                }
              ]
            },
            {
              "coindescs": [
                {
                  "desc": "[SuperCoin]"
                },
                {
                  "desc": "При 300+ [BloodDinner_Common_Accumulation]: Наносит +0.1% больше урона за каждое значение (макс. <style=\"highlight\">50</style>%)"
                },
                {
                  "desc": "[WinDuelAttack] Наносит [ThirstyRose] основываясь на наибольшем Абсолютном резон. Похоти (макс. <style=\"highlight\">4</style>)"
                }
              ]
            }
          ]
        }
      ]
    },
    {
      "id": 2030721,
      "levelList": [
        {
          "level": 1,
          "name": "Жаждущая - Миркалла",
          "abName": "Четыре сотни Роз",
          "desc": "[CantIdentify]\nСлучайные цели\nОЗ этого Грешника не может упасть ниже 1 при использовании этого ЭГО.\nЕсли на цели имеется 10+ [Laceration], Сила Монет -1\n[BeforeAttack] При значении меньше 150 [BloodDinner], наносит 1 [Laceration] за каждый удар\n[BeforeAttack] Получает 20 [Laceration], и сразу же активирует [Laceration] на себе. Теряет 2 счётчика [Laceration]",
          "coinlist": [
            {
              "coindescs": [
                {
                  "desc": "[OnSucceedAttack] Наносит 1 [Laceration] за каждые 50 [BloodDinner_Common_Accumulation] (макс. 10)"
                },
                {
                  "desc": "[OnSucceedAttack] При 100- [BloodDinner], наносит 10 [Laceration]"
                }
              ]
            },
            {
              "coindescs": [
                {
                  "desc": "Наносит +5% больше урона за каждые 100 [BloodDinner_Common_Accumulation] (макс. 25%)"
                },
                {
                  "desc": "[WinDuelAttack] Наносит [ThirstyRose] основываясь на наибольшем Абсолютном резон.е Похоти (макс. 3)"
                },
                {
                  "desc": "[WinDuelAttack] Исцеляет 50% ОЗ от нанесенного урона (макс. 10)"
                }
              ]
            }
          ]
        },
        {
          "level": 3,
          "name": "Жаждущая - Миркалла",
          "abName": "Четыре сотни Роз",
          "desc": "[CantIdentify]\nСлучайные цели\nОЗ этого Грешника не может упасть ниже 1 при использовании этого ЭГО.\nЕсли на цели имеется 10+ [Laceration], Сила Монет -1\n<style=\"highlight\">При 200+ [BloodDinner_Accumulation] этим Грешником, Сила Монет -1</style>\n[BeforeAttack] При значении меньше 150 [BloodDinner], наносит 1 [Laceration] за каждый удар\n[BeforeAttack] Получает 20 [Laceration], и сразу же активирует [Laceration] на себе. Теряет 2 счётчика [Laceration]",
          "coinlist": [
            {
              "coindescs": [
                {
                  "desc": "[OnSucceedAttack] Наносит 1 [Laceration] за каждые 50 [BloodDinner_Common_Accumulation] (макс. 10)<style=\"highlight\"></style>"
                },
                {
                  "desc": "[OnSucceedAttack] При 100- [BloodDinner], наносит 10 [Laceration]<style=\"highlight\"></style>"
                }
              ]
            },
            {
              "coindescs": [
                {
                  "desc": "Наносит +<style=\"highlight\">10</style>% больше урона за каждые 100 [BloodDinner_Common_Accumulation] (макс. <style=\"highlight\">50</style>%)"
                },
                {
                  "desc": "[WinDuelAttack] Наносит [ThirstyRose] основываясь на наибольшем Абсолютном резон. Похоти (макс. <style=\"highlight\">4</style>)"
                },
                {
                  "desc": "[WinDuelAttack] Исцеляет 50% ОЗ от нанесенного урона (макс. 10)"
                }
              ]
            }
          ]
        },
        {
          "level": 4,
          "name": "Жаждущая - Миркалла",
          "abName": "Четыре сотни Роз",
          "desc": "[CantIdentify]\nСлучайные цели\nОЗ этого Грешника не может упасть ниже 1 при использовании этого ЭГО.\nЕсли на цели имеется 10+ [Laceration], Сила Монет -1\nПри 200+ [BloodDinner_Accumulation] этим Грешником, Сила Монет -1\n[BeforeAttack] При значении меньше 150 [BloodDinner], наносит 1 [Laceration] за каждый удар\n[BeforeAttack] Получает 20 [Laceration], и сразу же активирует [Laceration] на себе. Теряет 2 счётчика [Laceration]<style=\"highlight\"></style>",
          "coinlist": [
            {
              "coindescs": [
                {
                  "desc": "[OnSucceedAttack] Наносит 1 [Laceration] за каждые 50 [BloodDinner_Common_Accumulation] (макс. 10)<style=\"highlight\"></style>"
                },
                {
                  "desc": "[OnSucceedAttack] При 100- [BloodDinner], наносит 10 [Laceration]<style=\"highlight\"></style>"
                }
              ]
            },
            {
              "coindescs": [
                {
                  "desc": "Наносит +<style=\"highlight\">20</style>% больше урона за каждые 100 [BloodDinner_Common_Accumulation] (макс. <style=\"highlight\">100</style>%)"
                },
                {
                  "desc": "[WinDuelAttack] Наносит [ThirstyRose] основываясь на наибольшем Абсолютном резон. Похоти (макс. <style=\"highlight\">5</style>)"
                },
                {
                  "desc": "[WinDuelAttack] Исцеляет 50% ОЗ от нанесенного урона (макс. 10)"
                }
              ]
            }
          ]
        }
      ]
    }
  ]
}
